{"metadata": {"dbt_schema_version": "https://schemas.getdbt.com/dbt/run-results/v6.json", "dbt_version": "1.8.8", "generated_at": "2024-11-01T06:41:55.416580Z", "invocation_id": "2f70a4a1-d426-4d53-bb97-e130871e5276", "env": {}}, "results": [{"status": "success", "timing": [{"name": "compile", "started_at": "2024-11-01T06:41:44.643077Z", "completed_at": "2024-11-01T06:41:44.965405Z"}, {"name": "execute", "started_at": "2024-11-01T06:41:44.966867Z", "completed_at": "2024-11-01T06:41:45.307648Z"}], "thread_id": "Thread-1 (worker)", "execution_time": 0.6710255146026611, "adapter_response": {"_message": "CREATE VIEW", "rows_affected": -1, "query": "/* {\"app\": \"dbt\", \"dbt_version\": \"1.8.8\", \"profile_name\": \"my_dbt_trino_project\", \"target_name\": \"dev\", \"node_id\": \"model.my_dbt_trino_project.base_table_claim\"} */\n\n  create or replace view\n    \"iceberg\".\"omop\".\"base_table_claim\"\n  security definer\n  as\n    \n\n\n\n\nwith source as (\n    select \n        \n            request_method as \"request_method\",\n        \n            request_url as \"request_url\",\n        \n            resource_id as \"resource_id\",\n        \n            resource_type as \"resource_type\",\n        \n            resource_status as \"resource_status\",\n        \n            full_url as \"full_url\",\n        \n            insurance as \"insurance\",\n        \n            identifier as \"identifier\",\n        \n            extension as \"extension\",\n        \n            item as \"item\",\n        \n            created as \"created\",\n        \n            use as \"use\",\n        \n            diagnosis as \"diagnosis\",\n        \n            procedure as \"procedure\",\n        \n            priority as \"priority\",\n        \n            type as \"type\",\n        \n            supportinginfo as \"supportinginfo\",\n        \n            provider as \"provider\",\n        \n            meta as \"meta\",\n        \n            patient as \"patient\",\n        \n            enterer as \"enterer\",\n        \n            subtype as \"subtype\",\n        \n            id as \"id\",\n        \n            resourcetype as \"resourcetype\",\n        \n            status as \"status\"\n        \n    from \"postgresql\".\"dbt\".\"fhir_data_claim\"\n)\n\nselect * from source\n  ", "query_id": "20241101_051146_02671_5mmc2"}, "message": "CREATE VIEW", "failures": null, "unique_id": "model.my_dbt_trino_project.base_table_claim", "compiled": true, "compiled_code": "\n\n\n\n\nwith source as (\n    select \n        \n            request_method as \"request_method\",\n        \n            request_url as \"request_url\",\n        \n            resource_id as \"resource_id\",\n        \n            resource_type as \"resource_type\",\n        \n            resource_status as \"resource_status\",\n        \n            full_url as \"full_url\",\n        \n            insurance as \"insurance\",\n        \n            identifier as \"identifier\",\n        \n            extension as \"extension\",\n        \n            item as \"item\",\n        \n            created as \"created\",\n        \n            use as \"use\",\n        \n            diagnosis as \"diagnosis\",\n        \n            procedure as \"procedure\",\n        \n            priority as \"priority\",\n        \n            type as \"type\",\n        \n            supportinginfo as \"supportinginfo\",\n        \n            provider as \"provider\",\n        \n            meta as \"meta\",\n        \n            patient as \"patient\",\n        \n            enterer as \"enterer\",\n        \n            subtype as \"subtype\",\n        \n            id as \"id\",\n        \n            resourcetype as \"resourcetype\",\n        \n            status as \"status\"\n        \n    from \"postgresql\".\"dbt\".\"fhir_data_claim\"\n)\n\nselect * from source", "relation_name": "\"iceberg\".\"omop\".\"base_table_claim\""}, {"status": "success", "timing": [{"name": "compile", "started_at": "2024-11-01T06:41:45.323994Z", "completed_at": "2024-11-01T06:41:45.572703Z"}, {"name": "execute", "started_at": "2024-11-01T06:41:45.574089Z", "completed_at": "2024-11-01T06:41:45.805710Z"}], "thread_id": "Thread-1 (worker)", "execution_time": 0.48770666122436523, "adapter_response": {"_message": "CREATE VIEW", "rows_affected": -1, "query": "/* {\"app\": \"dbt\", \"dbt_version\": \"1.8.8\", \"profile_name\": \"my_dbt_trino_project\", \"target_name\": \"dev\", \"node_id\": \"model.my_dbt_trino_project.base_table_coverage\"} */\n\n  create or replace view\n    \"iceberg\".\"omop\".\"base_table_coverage\"\n  security definer\n  as\n    \n\n\n\n\nwith source as (\n    select \n        \n            request_method as \"request_method\",\n        \n            request_url as \"request_url\",\n        \n            resource_id as \"resource_id\",\n        \n            resource_type as \"resource_type\",\n        \n            resource_status as \"resource_status\",\n        \n            full_url as \"full_url\",\n        \n            payor as \"payor\",\n        \n            beneficiary as \"beneficiary\",\n        \n            meta as \"meta\",\n        \n            id as \"id\",\n        \n            resourcetype as \"resourcetype\",\n        \n            status as \"status\"\n        \n    from \"postgresql\".\"dbt\".\"fhir_data_coverage\"\n)\n\nselect * from source\n  ", "query_id": "20241101_051147_02676_5mmc2"}, "message": "CREATE VIEW", "failures": null, "unique_id": "model.my_dbt_trino_project.base_table_coverage", "compiled": true, "compiled_code": "\n\n\n\n\nwith source as (\n    select \n        \n            request_method as \"request_method\",\n        \n            request_url as \"request_url\",\n        \n            resource_id as \"resource_id\",\n        \n            resource_type as \"resource_type\",\n        \n            resource_status as \"resource_status\",\n        \n            full_url as \"full_url\",\n        \n            payor as \"payor\",\n        \n            beneficiary as \"beneficiary\",\n        \n            meta as \"meta\",\n        \n            id as \"id\",\n        \n            resourcetype as \"resourcetype\",\n        \n            status as \"status\"\n        \n    from \"postgresql\".\"dbt\".\"fhir_data_coverage\"\n)\n\nselect * from source", "relation_name": "\"iceberg\".\"omop\".\"base_table_coverage\""}, {"status": "success", "timing": [{"name": "compile", "started_at": "2024-11-01T06:41:45.817312Z", "completed_at": "2024-11-01T06:41:46.102965Z"}, {"name": "execute", "started_at": "2024-11-01T06:41:46.105036Z", "completed_at": "2024-11-01T06:41:46.354066Z"}], "thread_id": "Thread-1 (worker)", "execution_time": 0.5403714179992676, "adapter_response": {"_message": "CREATE VIEW", "rows_affected": -1, "query": "/* {\"app\": \"dbt\", \"dbt_version\": \"1.8.8\", \"profile_name\": \"my_dbt_trino_project\", \"target_name\": \"dev\", \"node_id\": \"model.my_dbt_trino_project.base_table_diagnosticreport\"} */\n\n  create or replace view\n    \"iceberg\".\"omop\".\"base_table_diagnosticreport\"\n  security definer\n  as\n    \n\n\n\n\nwith source as (\n    select \n        \n            request_method as \"request_method\",\n        \n            request_url as \"request_url\",\n        \n            resource_id as \"resource_id\",\n        \n            resource_type as \"resource_type\",\n        \n            resource_status as \"resource_status\",\n        \n            full_url as \"full_url\",\n        \n            conclusion as \"conclusion\",\n        \n            code as \"code\",\n        \n            performer as \"performer\",\n        \n            effectivedatetime as \"effectivedatetime\",\n        \n            meta as \"meta\",\n        \n            subject as \"subject\",\n        \n            id as \"id\",\n        \n            media as \"media\",\n        \n            imagingstudy as \"imagingstudy\",\n        \n            resourcetype as \"resourcetype\",\n        \n            status as \"status\",\n        \n            presentedform as \"presentedform\"\n        \n    from \"postgresql\".\"dbt\".\"fhir_data_diagnosticreport\"\n)\n\nselect * from source\n  ", "query_id": "20241101_051147_02681_5mmc2"}, "message": "CREATE VIEW", "failures": null, "unique_id": "model.my_dbt_trino_project.base_table_diagnosticreport", "compiled": true, "compiled_code": "\n\n\n\n\nwith source as (\n    select \n        \n            request_method as \"request_method\",\n        \n            request_url as \"request_url\",\n        \n            resource_id as \"resource_id\",\n        \n            resource_type as \"resource_type\",\n        \n            resource_status as \"resource_status\",\n        \n            full_url as \"full_url\",\n        \n            conclusion as \"conclusion\",\n        \n            code as \"code\",\n        \n            performer as \"performer\",\n        \n            effectivedatetime as \"effectivedatetime\",\n        \n            meta as \"meta\",\n        \n            subject as \"subject\",\n        \n            id as \"id\",\n        \n            media as \"media\",\n        \n            imagingstudy as \"imagingstudy\",\n        \n            resourcetype as \"resourcetype\",\n        \n            status as \"status\",\n        \n            presentedform as \"presentedform\"\n        \n    from \"postgresql\".\"dbt\".\"fhir_data_diagnosticreport\"\n)\n\nselect * from source", "relation_name": "\"iceberg\".\"omop\".\"base_table_diagnosticreport\""}, {"status": "success", "timing": [{"name": "compile", "started_at": "2024-11-01T06:41:46.364855Z", "completed_at": "2024-11-01T06:41:46.598137Z"}, {"name": "execute", "started_at": "2024-11-01T06:41:46.599153Z", "completed_at": "2024-11-01T06:41:46.833291Z"}], "thread_id": "Thread-1 (worker)", "execution_time": 0.4732398986816406, "adapter_response": {"_message": "CREATE VIEW", "rows_affected": -1, "query": "/* {\"app\": \"dbt\", \"dbt_version\": \"1.8.8\", \"profile_name\": \"my_dbt_trino_project\", \"target_name\": \"dev\", \"node_id\": \"model.my_dbt_trino_project.base_table_documentreference\"} */\n\n  create or replace view\n    \"iceberg\".\"omop\".\"base_table_documentreference\"\n  security definer\n  as\n    \n\n\n\n\nwith source as (\n    select \n        \n            request_method as \"request_method\",\n        \n            request_url as \"request_url\",\n        \n            resource_id as \"resource_id\",\n        \n            resource_type as \"resource_type\",\n        \n            resource_status as \"resource_status\",\n        \n            full_url as \"full_url\",\n        \n            meta as \"meta\",\n        \n            subject as \"subject\",\n        \n            id as \"id\",\n        \n            category as \"category\",\n        \n            content as \"content\",\n        \n            resourcetype as \"resourcetype\",\n        \n            status as \"status\"\n        \n    from \"postgresql\".\"dbt\".\"fhir_data_documentreference\"\n)\n\nselect * from source\n  ", "query_id": "20241101_051148_02686_5mmc2"}, "message": "CREATE VIEW", "failures": null, "unique_id": "model.my_dbt_trino_project.base_table_documentreference", "compiled": true, "compiled_code": "\n\n\n\n\nwith source as (\n    select \n        \n            request_method as \"request_method\",\n        \n            request_url as \"request_url\",\n        \n            resource_id as \"resource_id\",\n        \n            resource_type as \"resource_type\",\n        \n            resource_status as \"resource_status\",\n        \n            full_url as \"full_url\",\n        \n            meta as \"meta\",\n        \n            subject as \"subject\",\n        \n            id as \"id\",\n        \n            category as \"category\",\n        \n            content as \"content\",\n        \n            resourcetype as \"resourcetype\",\n        \n            status as \"status\"\n        \n    from \"postgresql\".\"dbt\".\"fhir_data_documentreference\"\n)\n\nselect * from source", "relation_name": "\"iceberg\".\"omop\".\"base_table_documentreference\""}, {"status": "success", "timing": [{"name": "compile", "started_at": "2024-11-01T06:41:46.846682Z", "completed_at": "2024-11-01T06:41:47.038040Z"}, {"name": "execute", "started_at": "2024-11-01T06:41:47.039371Z", "completed_at": "2024-11-01T06:41:47.273268Z"}], "thread_id": "Thread-1 (worker)", "execution_time": 0.43392038345336914, "adapter_response": {"_message": "CREATE VIEW", "rows_affected": -1, "query": "/* {\"app\": \"dbt\", \"dbt_version\": \"1.8.8\", \"profile_name\": \"my_dbt_trino_project\", \"target_name\": \"dev\", \"node_id\": \"model.my_dbt_trino_project.base_table_encounter\"} */\n\n  create or replace view\n    \"iceberg\".\"omop\".\"base_table_encounter\"\n  security definer\n  as\n    \n\n\n\n\nwith source as (\n    select \n        \n            request_method as \"request_method\",\n        \n            request_url as \"request_url\",\n        \n            resource_id as \"resource_id\",\n        \n            resource_type as \"resource_type\",\n        \n            resource_status as \"resource_status\",\n        \n            full_url as \"full_url\",\n        \n            servicetype as \"servicetype\",\n        \n            meta as \"meta\",\n        \n            id as \"id\",\n        \n            class as \"class\",\n        \n            resourcetype as \"resourcetype\",\n        \n            status as \"status\"\n        \n    from \"postgresql\".\"dbt\".\"fhir_data_encounter\"\n)\n\nselect * from source\n  ", "query_id": "20241101_051148_02688_5mmc2"}, "message": "CREATE VIEW", "failures": null, "unique_id": "model.my_dbt_trino_project.base_table_encounter", "compiled": true, "compiled_code": "\n\n\n\n\nwith source as (\n    select \n        \n            request_method as \"request_method\",\n        \n            request_url as \"request_url\",\n        \n            resource_id as \"resource_id\",\n        \n            resource_type as \"resource_type\",\n        \n            resource_status as \"resource_status\",\n        \n            full_url as \"full_url\",\n        \n            servicetype as \"servicetype\",\n        \n            meta as \"meta\",\n        \n            id as \"id\",\n        \n            class as \"class\",\n        \n            resourcetype as \"resourcetype\",\n        \n            status as \"status\"\n        \n    from \"postgresql\".\"dbt\".\"fhir_data_encounter\"\n)\n\nselect * from source", "relation_name": "\"iceberg\".\"omop\".\"base_table_encounter\""}, {"status": "success", "timing": [{"name": "compile", "started_at": "2024-11-01T06:41:47.294053Z", "completed_at": "2024-11-01T06:41:47.489528Z"}, {"name": "execute", "started_at": "2024-11-01T06:41:47.491056Z", "completed_at": "2024-11-01T06:41:47.698005Z"}], "thread_id": "Thread-1 (worker)", "execution_time": 0.41156482696533203, "adapter_response": {"_message": "CREATE VIEW", "rows_affected": -1, "query": "/* {\"app\": \"dbt\", \"dbt_version\": \"1.8.8\", \"profile_name\": \"my_dbt_trino_project\", \"target_name\": \"dev\", \"node_id\": \"model.my_dbt_trino_project.base_table_imagingstudy\"} */\n\n  create or replace view\n    \"iceberg\".\"omop\".\"base_table_imagingstudy\"\n  security definer\n  as\n    \n\n\n\n\nwith source as (\n    select \n        \n            request_method as \"request_method\",\n        \n            request_url as \"request_url\",\n        \n            resource_id as \"resource_id\",\n        \n            resource_type as \"resource_type\",\n        \n            resource_status as \"resource_status\",\n        \n            full_url as \"full_url\",\n        \n            identifier as \"identifier\",\n        \n            meta as \"meta\",\n        \n            series as \"series\",\n        \n            subject as \"subject\",\n        \n            id as \"id\",\n        \n            resourcetype as \"resourcetype\",\n        \n            status as \"status\"\n        \n    from \"postgresql\".\"dbt\".\"fhir_data_imagingstudy\"\n)\n\nselect * from source\n  ", "query_id": "20241101_051149_02690_5mmc2"}, "message": "CREATE VIEW", "failures": null, "unique_id": "model.my_dbt_trino_project.base_table_imagingstudy", "compiled": true, "compiled_code": "\n\n\n\n\nwith source as (\n    select \n        \n            request_method as \"request_method\",\n        \n            request_url as \"request_url\",\n        \n            resource_id as \"resource_id\",\n        \n            resource_type as \"resource_type\",\n        \n            resource_status as \"resource_status\",\n        \n            full_url as \"full_url\",\n        \n            identifier as \"identifier\",\n        \n            meta as \"meta\",\n        \n            series as \"series\",\n        \n            subject as \"subject\",\n        \n            id as \"id\",\n        \n            resourcetype as \"resourcetype\",\n        \n            status as \"status\"\n        \n    from \"postgresql\".\"dbt\".\"fhir_data_imagingstudy\"\n)\n\nselect * from source", "relation_name": "\"iceberg\".\"omop\".\"base_table_imagingstudy\""}, {"status": "success", "timing": [{"name": "compile", "started_at": "2024-11-01T06:41:47.708630Z", "completed_at": "2024-11-01T06:41:47.911455Z"}, {"name": "execute", "started_at": "2024-11-01T06:41:47.912860Z", "completed_at": "2024-11-01T06:41:48.108245Z"}], "thread_id": "Thread-1 (worker)", "execution_time": 0.4035177230834961, "adapter_response": {"_message": "CREATE VIEW", "rows_affected": -1, "query": "/* {\"app\": \"dbt\", \"dbt_version\": \"1.8.8\", \"profile_name\": \"my_dbt_trino_project\", \"target_name\": \"dev\", \"node_id\": \"model.my_dbt_trino_project.base_table_media\"} */\n\n  create or replace view\n    \"iceberg\".\"omop\".\"base_table_media\"\n  security definer\n  as\n    \n\n\n\n\nwith source as (\n    select \n        \n            request_method as \"request_method\",\n        \n            request_url as \"request_url\",\n        \n            resource_id as \"resource_id\",\n        \n            resource_type as \"resource_type\",\n        \n            resource_status as \"resource_status\",\n        \n            full_url as \"full_url\",\n        \n            bodysite as \"bodysite\",\n        \n            meta as \"meta\",\n        \n            subject as \"subject\",\n        \n            id as \"id\",\n        \n            content as \"content\",\n        \n            resourcetype as \"resourcetype\",\n        \n            status as \"status\"\n        \n    from \"postgresql\".\"dbt\".\"fhir_data_media\"\n)\n\nselect * from source\n  ", "query_id": "20241101_051149_02692_5mmc2"}, "message": "CREATE VIEW", "failures": null, "unique_id": "model.my_dbt_trino_project.base_table_media", "compiled": true, "compiled_code": "\n\n\n\n\nwith source as (\n    select \n        \n            request_method as \"request_method\",\n        \n            request_url as \"request_url\",\n        \n            resource_id as \"resource_id\",\n        \n            resource_type as \"resource_type\",\n        \n            resource_status as \"resource_status\",\n        \n            full_url as \"full_url\",\n        \n            bodysite as \"bodysite\",\n        \n            meta as \"meta\",\n        \n            subject as \"subject\",\n        \n            id as \"id\",\n        \n            content as \"content\",\n        \n            resourcetype as \"resourcetype\",\n        \n            status as \"status\"\n        \n    from \"postgresql\".\"dbt\".\"fhir_data_media\"\n)\n\nselect * from source", "relation_name": "\"iceberg\".\"omop\".\"base_table_media\""}, {"status": "success", "timing": [{"name": "compile", "started_at": "2024-11-01T06:41:48.119266Z", "completed_at": "2024-11-01T06:41:48.303287Z"}, {"name": "execute", "started_at": "2024-11-01T06:41:48.304299Z", "completed_at": "2024-11-01T06:41:48.519703Z"}], "thread_id": "Thread-1 (worker)", "execution_time": 0.4057495594024658, "adapter_response": {"_message": "CREATE VIEW", "rows_affected": -1, "query": "/* {\"app\": \"dbt\", \"dbt_version\": \"1.8.8\", \"profile_name\": \"my_dbt_trino_project\", \"target_name\": \"dev\", \"node_id\": \"model.my_dbt_trino_project.base_table_medicationrequest\"} */\n\n  create or replace view\n    \"iceberg\".\"omop\".\"base_table_medicationrequest\"\n  security definer\n  as\n    \n\n\n\n\nwith source as (\n    select \n        \n            request_method as \"request_method\",\n        \n            request_url as \"request_url\",\n        \n            resource_id as \"resource_id\",\n        \n            resource_type as \"resource_type\",\n        \n            resource_status as \"resource_status\",\n        \n            full_url as \"full_url\",\n        \n            dosageinstruction as \"dosageinstruction\",\n        \n            dispenserequest as \"dispenserequest\",\n        \n            meta as \"meta\",\n        \n            subject as \"subject\",\n        \n            id as \"id\",\n        \n            category as \"category\",\n        \n            medicationcodeableconcept as \"medicationcodeableconcept\",\n        \n            intent as \"intent\",\n        \n            resourcetype as \"resourcetype\",\n        \n            status as \"status\",\n        \n            statusreason as \"statusreason\"\n        \n    from \"postgresql\".\"dbt\".\"fhir_data_medicationrequest\"\n)\n\nselect * from source\n  ", "query_id": "20241101_051150_02694_5mmc2"}, "message": "CREATE VIEW", "failures": null, "unique_id": "model.my_dbt_trino_project.base_table_medicationrequest", "compiled": true, "compiled_code": "\n\n\n\n\nwith source as (\n    select \n        \n            request_method as \"request_method\",\n        \n            request_url as \"request_url\",\n        \n            resource_id as \"resource_id\",\n        \n            resource_type as \"resource_type\",\n        \n            resource_status as \"resource_status\",\n        \n            full_url as \"full_url\",\n        \n            dosageinstruction as \"dosageinstruction\",\n        \n            dispenserequest as \"dispenserequest\",\n        \n            meta as \"meta\",\n        \n            subject as \"subject\",\n        \n            id as \"id\",\n        \n            category as \"category\",\n        \n            medicationcodeableconcept as \"medicationcodeableconcept\",\n        \n            intent as \"intent\",\n        \n            resourcetype as \"resourcetype\",\n        \n            status as \"status\",\n        \n            statusreason as \"statusreason\"\n        \n    from \"postgresql\".\"dbt\".\"fhir_data_medicationrequest\"\n)\n\nselect * from source", "relation_name": "\"iceberg\".\"omop\".\"base_table_medicationrequest\""}, {"status": "success", "timing": [{"name": "compile", "started_at": "2024-11-01T06:41:48.533166Z", "completed_at": "2024-11-01T06:41:48.728381Z"}, {"name": "execute", "started_at": "2024-11-01T06:41:48.730012Z", "completed_at": "2024-11-01T06:41:48.954105Z"}], "thread_id": "Thread-1 (worker)", "execution_time": 0.4261009693145752, "adapter_response": {"_message": "CREATE VIEW", "rows_affected": -1, "query": "/* {\"app\": \"dbt\", \"dbt_version\": \"1.8.8\", \"profile_name\": \"my_dbt_trino_project\", \"target_name\": \"dev\", \"node_id\": \"model.my_dbt_trino_project.base_table_observation\"} */\n\n  create or replace view\n    \"iceberg\".\"omop\".\"base_table_observation\"\n  security definer\n  as\n    \n\n\n\n\nwith source as (\n    select \n        \n            request_method as \"request_method\",\n        \n            request_url as \"request_url\",\n        \n            resource_id as \"resource_id\",\n        \n            resource_type as \"resource_type\",\n        \n            resource_status as \"resource_status\",\n        \n            full_url as \"full_url\",\n        \n            valuecodeableconcept as \"valuecodeableconcept\",\n        \n            performer as \"performer\",\n        \n            code as \"code\",\n        \n            effectivedatetime as \"effectivedatetime\",\n        \n            meta as \"meta\",\n        \n            subject as \"subject\",\n        \n            id as \"id\",\n        \n            resourcetype as \"resourcetype\",\n        \n            status as \"status\",\n        \n            valuestring as \"valuestring\",\n        \n            method as \"method\",\n        \n            component as \"component\",\n        \n            interpretation as \"interpretation\",\n        \n            specimen as \"specimen\",\n        \n            derivedfrom as \"derivedfrom\",\n        \n            category as \"category\",\n        \n            referencerange as \"referencerange\",\n        \n            valuequantity as \"valuequantity\"\n        \n    from \"postgresql\".\"dbt\".\"fhir_data_observation\"\n)\n\nselect * from source\n  ", "query_id": "20241101_051150_02696_5mmc2"}, "message": "CREATE VIEW", "failures": null, "unique_id": "model.my_dbt_trino_project.base_table_observation", "compiled": true, "compiled_code": "\n\n\n\n\nwith source as (\n    select \n        \n            request_method as \"request_method\",\n        \n            request_url as \"request_url\",\n        \n            resource_id as \"resource_id\",\n        \n            resource_type as \"resource_type\",\n        \n            resource_status as \"resource_status\",\n        \n            full_url as \"full_url\",\n        \n            valuecodeableconcept as \"valuecodeableconcept\",\n        \n            performer as \"performer\",\n        \n            code as \"code\",\n        \n            effectivedatetime as \"effectivedatetime\",\n        \n            meta as \"meta\",\n        \n            subject as \"subject\",\n        \n            id as \"id\",\n        \n            resourcetype as \"resourcetype\",\n        \n            status as \"status\",\n        \n            valuestring as \"valuestring\",\n        \n            method as \"method\",\n        \n            component as \"component\",\n        \n            interpretation as \"interpretation\",\n        \n            specimen as \"specimen\",\n        \n            derivedfrom as \"derivedfrom\",\n        \n            category as \"category\",\n        \n            referencerange as \"referencerange\",\n        \n            valuequantity as \"valuequantity\"\n        \n    from \"postgresql\".\"dbt\".\"fhir_data_observation\"\n)\n\nselect * from source", "relation_name": "\"iceberg\".\"omop\".\"base_table_observation\""}, {"status": "success", "timing": [{"name": "compile", "started_at": "2024-11-01T06:41:48.966545Z", "completed_at": "2024-11-01T06:41:49.157112Z"}, {"name": "execute", "started_at": "2024-11-01T06:41:49.158199Z", "completed_at": "2024-11-01T06:41:49.366038Z"}], "thread_id": "Thread-1 (worker)", "execution_time": 0.404282808303833, "adapter_response": {"_message": "CREATE VIEW", "rows_affected": -1, "query": "/* {\"app\": \"dbt\", \"dbt_version\": \"1.8.8\", \"profile_name\": \"my_dbt_trino_project\", \"target_name\": \"dev\", \"node_id\": \"model.my_dbt_trino_project.base_table_organization\"} */\n\n  create or replace view\n    \"iceberg\".\"omop\".\"base_table_organization\"\n  security definer\n  as\n    \n\n\n\n\nwith source as (\n    select \n        \n            request_method as \"request_method\",\n        \n            request_url as \"request_url\",\n        \n            resource_id as \"resource_id\",\n        \n            resource_type as \"resource_type\",\n        \n            resource_status as \"resource_status\",\n        \n            full_url as \"full_url\",\n        \n            identifier as \"identifier\",\n        \n            meta as \"meta\",\n        \n            name as \"name\",\n        \n            id as \"id\",\n        \n            type as \"type\",\n        \n            resourcetype as \"resourcetype\"\n        \n    from \"postgresql\".\"dbt\".\"fhir_data_organization\"\n)\n\nselect * from source\n  ", "query_id": "20241101_051150_02698_5mmc2"}, "message": "CREATE VIEW", "failures": null, "unique_id": "model.my_dbt_trino_project.base_table_organization", "compiled": true, "compiled_code": "\n\n\n\n\nwith source as (\n    select \n        \n            request_method as \"request_method\",\n        \n            request_url as \"request_url\",\n        \n            resource_id as \"resource_id\",\n        \n            resource_type as \"resource_type\",\n        \n            resource_status as \"resource_status\",\n        \n            full_url as \"full_url\",\n        \n            identifier as \"identifier\",\n        \n            meta as \"meta\",\n        \n            name as \"name\",\n        \n            id as \"id\",\n        \n            type as \"type\",\n        \n            resourcetype as \"resourcetype\"\n        \n    from \"postgresql\".\"dbt\".\"fhir_data_organization\"\n)\n\nselect * from source", "relation_name": "\"iceberg\".\"omop\".\"base_table_organization\""}, {"status": "success", "timing": [{"name": "compile", "started_at": "2024-11-01T06:41:49.378498Z", "completed_at": "2024-11-01T06:41:49.535391Z"}, {"name": "execute", "started_at": "2024-11-01T06:41:49.537392Z", "completed_at": "2024-11-01T06:41:49.741644Z"}], "thread_id": "Thread-1 (worker)", "execution_time": 0.3682725429534912, "adapter_response": {"_message": "CREATE VIEW", "rows_affected": -1, "query": "/* {\"app\": \"dbt\", \"dbt_version\": \"1.8.8\", \"profile_name\": \"my_dbt_trino_project\", \"target_name\": \"dev\", \"node_id\": \"model.my_dbt_trino_project.base_table_patient\"} */\n\n  create or replace view\n    \"iceberg\".\"omop\".\"base_table_patient\"\n  security definer\n  as\n    \n\n\n\n\nwith source as (\n    select \n        \n            request_method as \"request_method\",\n        \n            request_url as \"request_url\",\n        \n            resource_id as \"resource_id\",\n        \n            resource_type as \"resource_type\",\n        \n            resource_status as \"resource_status\",\n        \n            full_url as \"full_url\",\n        \n            identifier as \"identifier\",\n        \n            gender as \"gender\",\n        \n            meta as \"meta\",\n        \n            name as \"name\",\n        \n            id as \"id\",\n        \n            birthdate as \"birthdate\",\n        \n            resourcetype as \"resourcetype\"\n        \n    from \"postgresql\".\"dbt\".\"fhir_data_patient\"\n)\n\nselect * from source\n  ", "query_id": "20241101_051151_02700_5mmc2"}, "message": "CREATE VIEW", "failures": null, "unique_id": "model.my_dbt_trino_project.base_table_patient", "compiled": true, "compiled_code": "\n\n\n\n\nwith source as (\n    select \n        \n            request_method as \"request_method\",\n        \n            request_url as \"request_url\",\n        \n            resource_id as \"resource_id\",\n        \n            resource_type as \"resource_type\",\n        \n            resource_status as \"resource_status\",\n        \n            full_url as \"full_url\",\n        \n            identifier as \"identifier\",\n        \n            gender as \"gender\",\n        \n            meta as \"meta\",\n        \n            name as \"name\",\n        \n            id as \"id\",\n        \n            birthdate as \"birthdate\",\n        \n            resourcetype as \"resourcetype\"\n        \n    from \"postgresql\".\"dbt\".\"fhir_data_patient\"\n)\n\nselect * from source", "relation_name": "\"iceberg\".\"omop\".\"base_table_patient\""}, {"status": "success", "timing": [{"name": "compile", "started_at": "2024-11-01T06:41:49.753432Z", "completed_at": "2024-11-01T06:41:49.919977Z"}, {"name": "execute", "started_at": "2024-11-01T06:41:49.920986Z", "completed_at": "2024-11-01T06:41:50.121612Z"}], "thread_id": "Thread-1 (worker)", "execution_time": 0.37319183349609375, "adapter_response": {"_message": "CREATE VIEW", "rows_affected": -1, "query": "/* {\"app\": \"dbt\", \"dbt_version\": \"1.8.8\", \"profile_name\": \"my_dbt_trino_project\", \"target_name\": \"dev\", \"node_id\": \"model.my_dbt_trino_project.base_table_practitioner\"} */\n\n  create or replace view\n    \"iceberg\".\"omop\".\"base_table_practitioner\"\n  security definer\n  as\n    \n\n\n\n\nwith source as (\n    select \n        \n            request_method as \"request_method\",\n        \n            request_url as \"request_url\",\n        \n            resource_id as \"resource_id\",\n        \n            resource_type as \"resource_type\",\n        \n            resource_status as \"resource_status\",\n        \n            full_url as \"full_url\",\n        \n            identifier as \"identifier\",\n        \n            meta as \"meta\",\n        \n            id as \"id\",\n        \n            resourcetype as \"resourcetype\"\n        \n    from \"postgresql\".\"dbt\".\"fhir_data_practitioner\"\n)\n\nselect * from source\n  ", "query_id": "20241101_051151_02702_5mmc2"}, "message": "CREATE VIEW", "failures": null, "unique_id": "model.my_dbt_trino_project.base_table_practitioner", "compiled": true, "compiled_code": "\n\n\n\n\nwith source as (\n    select \n        \n            request_method as \"request_method\",\n        \n            request_url as \"request_url\",\n        \n            resource_id as \"resource_id\",\n        \n            resource_type as \"resource_type\",\n        \n            resource_status as \"resource_status\",\n        \n            full_url as \"full_url\",\n        \n            identifier as \"identifier\",\n        \n            meta as \"meta\",\n        \n            id as \"id\",\n        \n            resourcetype as \"resourcetype\"\n        \n    from \"postgresql\".\"dbt\".\"fhir_data_practitioner\"\n)\n\nselect * from source", "relation_name": "\"iceberg\".\"omop\".\"base_table_practitioner\""}, {"status": "success", "timing": [{"name": "compile", "started_at": "2024-11-01T06:41:50.132448Z", "completed_at": "2024-11-01T06:41:50.313299Z"}, {"name": "execute", "started_at": "2024-11-01T06:41:50.314728Z", "completed_at": "2024-11-01T06:41:50.511440Z"}], "thread_id": "Thread-1 (worker)", "execution_time": 0.38527965545654297, "adapter_response": {"_message": "CREATE VIEW", "rows_affected": -1, "query": "/* {\"app\": \"dbt\", \"dbt_version\": \"1.8.8\", \"profile_name\": \"my_dbt_trino_project\", \"target_name\": \"dev\", \"node_id\": \"model.my_dbt_trino_project.base_table_procedure\"} */\n\n  create or replace view\n    \"iceberg\".\"omop\".\"base_table_procedure\"\n  security definer\n  as\n    \n\n\n\n\nwith source as (\n    select \n        \n            request_method as \"request_method\",\n        \n            request_url as \"request_url\",\n        \n            resource_id as \"resource_id\",\n        \n            resource_type as \"resource_type\",\n        \n            resource_status as \"resource_status\",\n        \n            full_url as \"full_url\",\n        \n            code as \"code\",\n        \n            meta as \"meta\",\n        \n            subject as \"subject\",\n        \n            usedreference as \"usedreference\",\n        \n            id as \"id\",\n        \n            performeddatetime as \"performeddatetime\",\n        \n            resourcetype as \"resourcetype\",\n        \n            status as \"status\"\n        \n    from \"postgresql\".\"dbt\".\"fhir_data_procedure\"\n)\n\nselect * from source\n  ", "query_id": "20241101_051152_02704_5mmc2"}, "message": "CREATE VIEW", "failures": null, "unique_id": "model.my_dbt_trino_project.base_table_procedure", "compiled": true, "compiled_code": "\n\n\n\n\nwith source as (\n    select \n        \n            request_method as \"request_method\",\n        \n            request_url as \"request_url\",\n        \n            resource_id as \"resource_id\",\n        \n            resource_type as \"resource_type\",\n        \n            resource_status as \"resource_status\",\n        \n            full_url as \"full_url\",\n        \n            code as \"code\",\n        \n            meta as \"meta\",\n        \n            subject as \"subject\",\n        \n            usedreference as \"usedreference\",\n        \n            id as \"id\",\n        \n            performeddatetime as \"performeddatetime\",\n        \n            resourcetype as \"resourcetype\",\n        \n            status as \"status\"\n        \n    from \"postgresql\".\"dbt\".\"fhir_data_procedure\"\n)\n\nselect * from source", "relation_name": "\"iceberg\".\"omop\".\"base_table_procedure\""}, {"status": "success", "timing": [{"name": "compile", "started_at": "2024-11-01T06:41:50.523757Z", "completed_at": "2024-11-01T06:41:50.705094Z"}, {"name": "execute", "started_at": "2024-11-01T06:41:50.706114Z", "completed_at": "2024-11-01T06:41:50.927021Z"}], "thread_id": "Thread-1 (worker)", "execution_time": 0.408550500869751, "adapter_response": {"_message": "CREATE VIEW", "rows_affected": -1, "query": "/* {\"app\": \"dbt\", \"dbt_version\": \"1.8.8\", \"profile_name\": \"my_dbt_trino_project\", \"target_name\": \"dev\", \"node_id\": \"model.my_dbt_trino_project.base_table_specimen\"} */\n\n  create or replace view\n    \"iceberg\".\"omop\".\"base_table_specimen\"\n  security definer\n  as\n    \n\n\n\n\nwith source as (\n    select \n        \n            request_method as \"request_method\",\n        \n            request_url as \"request_url\",\n        \n            resource_id as \"resource_id\",\n        \n            resource_type as \"resource_type\",\n        \n            resource_status as \"resource_status\",\n        \n            full_url as \"full_url\",\n        \n            meta as \"meta\",\n        \n            subject as \"subject\",\n        \n            receivedtime as \"receivedtime\",\n        \n            id as \"id\",\n        \n            type as \"type\",\n        \n            resourcetype as \"resourcetype\"\n        \n    from \"postgresql\".\"dbt\".\"fhir_data_specimen\"\n)\n\nselect * from source\n  ", "query_id": "20241101_051152_02706_5mmc2"}, "message": "CREATE VIEW", "failures": null, "unique_id": "model.my_dbt_trino_project.base_table_specimen", "compiled": true, "compiled_code": "\n\n\n\n\nwith source as (\n    select \n        \n            request_method as \"request_method\",\n        \n            request_url as \"request_url\",\n        \n            resource_id as \"resource_id\",\n        \n            resource_type as \"resource_type\",\n        \n            resource_status as \"resource_status\",\n        \n            full_url as \"full_url\",\n        \n            meta as \"meta\",\n        \n            subject as \"subject\",\n        \n            receivedtime as \"receivedtime\",\n        \n            id as \"id\",\n        \n            type as \"type\",\n        \n            resourcetype as \"resourcetype\"\n        \n    from \"postgresql\".\"dbt\".\"fhir_data_specimen\"\n)\n\nselect * from source", "relation_name": "\"iceberg\".\"omop\".\"base_table_specimen\""}, {"status": "success", "timing": [{"name": "compile", "started_at": "2024-11-01T06:41:50.957052Z", "completed_at": "2024-11-01T06:41:51.147630Z"}, {"name": "execute", "started_at": "2024-11-01T06:41:51.148632Z", "completed_at": "2024-11-01T06:41:51.350906Z"}], "thread_id": "Thread-1 (worker)", "execution_time": 0.40073513984680176, "adapter_response": {"_message": "CREATE VIEW", "rows_affected": -1, "query": "/* {\"app\": \"dbt\", \"dbt_version\": \"1.8.8\", \"profile_name\": \"my_dbt_trino_project\", \"target_name\": \"dev\", \"node_id\": \"model.my_dbt_trino_project.base_table_substance\"} */\n\n  create or replace view\n    \"iceberg\".\"omop\".\"base_table_substance\"\n  security definer\n  as\n    \n\n\n\n\nwith source as (\n    select \n        \n            request_method as \"request_method\",\n        \n            request_url as \"request_url\",\n        \n            resource_id as \"resource_id\",\n        \n            resource_type as \"resource_type\",\n        \n            resource_status as \"resource_status\",\n        \n            full_url as \"full_url\",\n        \n            code as \"code\",\n        \n            ingredient as \"ingredient\",\n        \n            meta as \"meta\",\n        \n            id as \"id\",\n        \n            resourcetype as \"resourcetype\"\n        \n    from \"postgresql\".\"dbt\".\"fhir_data_substance\"\n)\n\nselect * from source\n  ", "query_id": "20241101_051152_02708_5mmc2"}, "message": "CREATE VIEW", "failures": null, "unique_id": "model.my_dbt_trino_project.base_table_substance", "compiled": true, "compiled_code": "\n\n\n\n\nwith source as (\n    select \n        \n            request_method as \"request_method\",\n        \n            request_url as \"request_url\",\n        \n            resource_id as \"resource_id\",\n        \n            resource_type as \"resource_type\",\n        \n            resource_status as \"resource_status\",\n        \n            full_url as \"full_url\",\n        \n            code as \"code\",\n        \n            ingredient as \"ingredient\",\n        \n            meta as \"meta\",\n        \n            id as \"id\",\n        \n            resourcetype as \"resourcetype\"\n        \n    from \"postgresql\".\"dbt\".\"fhir_data_substance\"\n)\n\nselect * from source", "relation_name": "\"iceberg\".\"omop\".\"base_table_substance\""}], "elapsed_time": 11.811912298202515, "args": {"log_level": "info", "log_format_file": "json", "populate_cache": true, "resource_types": [], "source_freshness_run_project_hooks": false, "indirect_selection": "eager", "partial_parse_file_diff": true, "exclude_resource_types": [], "which": "build", "exclude": [], "partial_parse": true, "introspect": true, "project_dir": "C:\\Users\\ASUS\\Desktop\\work\\datalake\\dbt-omop", "use_colors_file": true, "favor_state": false, "use_colors": true, "log_file_max_bytes": 10485760, "empty": false, "show": false, "vars": {}, "log_path": "C:\\Users\\ASUS\\Desktop\\work\\datalake\\dbt-omop\\target\\my_dbt_trino_project_dbt_assets-0ff2ede-fb6b895", "defer": false, "export_saved_queries": false, "select": ["my_dbt_trino_project.sources.base_table_organization", "my_dbt_trino_project.sources.base_table_substance", "my_dbt_trino_project.sources.base_table_encounter", "my_dbt_trino_project.sources.base_table_documentreference", "my_dbt_trino_project.sources.base_table_media", "my_dbt_trino_project.sources.base_table_medicationrequest", "my_dbt_trino_project.sources.base_table_procedure", "my_dbt_trino_project.sources.base_table_specimen", "my_dbt_trino_project.sources.base_table_diagnosticreport", "my_dbt_trino_project.sources.base_table_imagingstudy", "my_dbt_trino_project.sources.base_table_patient", "my_dbt_trino_project.sources.base_table_claim", "my_dbt_trino_project.sources.base_table_coverage", "my_dbt_trino_project.sources.base_table_observation", "my_dbt_trino_project.sources.base_table_practitioner"], "strict_mode": false, "target_path": "target\\my_dbt_trino_project_dbt_assets-0ff2ede-fb6b895", "send_anonymous_usage_stats": false, "require_explicit_package_overrides_for_builtin_materializations": true, "enable_legacy_logger": false, "log_level_file": "debug", "macro_debugging": false, "log_format": "json", "cache_selected_only": false, "write_json": true, "invocation_command": "dbt build --select my_dbt_trino_project.sources.base_table_organization my_dbt_trino_project.sources.base_table_substance my_dbt_trino_project.sources.base_table_encounter my_dbt_trino_project.sources.base_table_documentreference my_dbt_trino_project.sources.base_table_media my_dbt_trino_project.sources.base_table_medicationrequest my_dbt_trino_project.sources.base_table_procedure my_dbt_trino_project.sources.base_table_specimen my_dbt_trino_project.sources.base_table_diagnosticreport my_dbt_trino_project.sources.base_table_imagingstudy my_dbt_trino_project.sources.base_table_patient my_dbt_trino_project.sources.base_table_claim my_dbt_trino_project.sources.base_table_coverage my_dbt_trino_project.sources.base_table_observation my_dbt_trino_project.sources.base_table_practitioner", "show_resource_report": false, "version_check": true, "require_resource_names_without_spaces": false, "warn_error_options": {"include": [], "exclude": []}, "print": true, "static_parser": true, "quiet": false, "profiles_dir": "C:\\Users\\ASUS\\Desktop\\work\\datalake\\dbt-omop", "include_saved_query": false, "printer_width": 80}}